slicenet/__init__.py
slicenet/cli/__init__.py
slicenet/cli/cli.py
slicenet/entities/__init__.py
slicenet/entities/base.py
slicenet/entities/cloud.py
slicenet/entities/nf.py
slicenet/entities/service.py
slicenet/entities/slicelet.py
slicenet/entities/staticslice.py
slicenet/mgrs/__init__.py
slicenet/mgrs/nfMgr.py
slicenet/mgrs/serviceMgr.py
slicenet/mgrs/sliceMgr.py
slicenet/utils/__init__.py
slicenet/utils/experiment.py
slicenet/utils/experimentMgr.py
slicenet/utils/slicenetlogger.py
slicenet/utils/util.py
slicenet-0.1.2.dist-info/LICENSE
slicenet-0.1.2.dist-info/METADATA
slicenet-0.1.2.dist-info/WHEEL
slicenet-0.1.2.dist-info/entry_points.txt
slicenet-0.1.2.dist-info/top_level.txt
slicenet-0.1.2.dist-info/RECORD
