Metadata-Version: 2.1
Name: slicenet
Version: 0.1.2
Summary: mininet-like simulation for Network Slices
Home-page: https://kspviswa.github.io/slicenet-pages/
Author: Viswa Kumar
Author-email: kspviswaphd@gmail.com
License: MIT
Classifier: Development Status :: 3 - Alpha
Classifier: License :: OSI Approved :: MIT License
Classifier: Programming Language :: Python :: 3.10
Classifier: Operating System :: OS Independent
Requires-Python: >=3.10
License-File: LICENSE
Requires-Dist: certifi ==2023.7.22
Requires-Dist: charset-normalizer ==3.3.1
Requires-Dist: click ==8.1.7
Requires-Dist: docutils ==0.20.1
Requires-Dist: idna ==3.4
Requires-Dist: importlib-metadata ==6.8.0
Requires-Dist: jaraco.classes ==3.3.0
Requires-Dist: keyring ==24.2.0
Requires-Dist: markdown-it-py ==3.0.0
Requires-Dist: mdurl ==0.1.2
Requires-Dist: more-itertools ==10.1.0
Requires-Dist: nh3 ==0.2.14
Requires-Dist: pkginfo ==1.9.6
Requires-Dist: Pygments ==2.16.1
Requires-Dist: PyYAML ==6.0.1
Requires-Dist: prompt-toolkit ==3.0.43
Requires-Dist: readerwriterlock ==1.0.9
Requires-Dist: readme-renderer ==42.0
Requires-Dist: requests ==2.31.0
Requires-Dist: requests-toolbelt ==1.0.0
Requires-Dist: rfc3986 ==2.0.0
Requires-Dist: rich ==13.6.0
Requires-Dist: semver ==3.0.2
Requires-Dist: tabulate ==0.9.0
Requires-Dist: twine ==4.0.2
Requires-Dist: typing-extensions >=4.8.0
Requires-Dist: urllib3 ==2.0.7
Requires-Dist: wheel ==0.42.0
Requires-Dist: zipp ==3.17.0
Requires-Dist: numpy ==2.2.1
